sdn_vehicle_test/__init__.py
sdn_vehicle_test/in_memory_simple_car_repository.py
sdn_vehicle_test/simple_car.py
sdn_vehicle_test-0.6.0.dist-info/licenses/LICENSE
sdn_vehicle_test-0.6.0.dist-info/METADATA
sdn_vehicle_test-0.6.0.dist-info/WHEEL
sdn_vehicle_test-0.6.0.dist-info/top_level.txt
sdn_vehicle_test-0.6.0.dist-info/RECORD
